owmeta_pytest_plugin/__init__.py
owmeta_pytest_plugin/pytest-cov-embed.py
owmeta_pytest_plugin/pytest_cov_embed.py
owmeta_pytest_plugin-0.0.8.dist-info/LICENSE.txt
owmeta_pytest_plugin-0.0.8.dist-info/METADATA
owmeta_pytest_plugin-0.0.8.dist-info/WHEEL
owmeta_pytest_plugin-0.0.8.dist-info/entry_points.txt
owmeta_pytest_plugin-0.0.8.dist-info/top_level.txt
owmeta_pytest_plugin-0.0.8.dist-info/RECORD
