Metadata-Version: 2.1
Name: owmeta-pytest-plugin
Version: 0.0.8
Summary: owmeta-pytest-plugin is a pytest plugin to aid in testing packages using owemta-core
Home-page: https://github.com/openworm/owmeta-pytest-plugin/
Author: OpenWorm.org authors and contributors
Author-email: info@openworm.org
License: MIT
Classifier: Intended Audience :: Science/Research
Classifier: License :: OSI Approved :: MIT License
Classifier: Framework :: Pytest
Classifier: Natural Language :: English
Classifier: Operating System :: OS Independent
Classifier: Programming Language :: Python :: 3.6
Classifier: Programming Language :: Python :: 3.7
Classifier: Programming Language :: Python :: 3.8
Classifier: Programming Language :: Python :: 3.9
Classifier: Programming Language :: Python :: 3.10
Classifier: Topic :: Scientific/Engineering
License-File: LICENSE.txt
Requires-Dist: pytest
